{
  "ABIRoot": {
    "kind": "Root",
    "name": "BidmadAdpieAdapter",
    "printedName": "BidmadAdpieAdapter",
    "children": [
      {
        "kind": "Import",
        "name": "AdPieSDK",
        "printedName": "AdPieSDK",
        "declKind": "Import",
        "moduleName": "BidmadAdpieAdapter",
        "declAttributes": [
          "RawDocComment"
        ]
      },
      {
        "kind": "Import",
        "name": "AdPieSDK",
        "printedName": "AdPieSDK",
        "declKind": "Import",
        "moduleName": "BidmadAdpieAdapter"
      },
      {
        "kind": "Import",
        "name": "UIKit",
        "printedName": "UIKit",
        "declKind": "Import",
        "moduleName": "BidmadAdpieAdapter",
        "declAttributes": [
          "RawDocComment"
        ]
      },
      {
        "kind": "Import",
        "name": "BidmadSDK",
        "printedName": "BidmadSDK",
        "declKind": "Import",
        "moduleName": "BidmadAdpieAdapter"
      },
      {
        "kind": "Import",
        "name": "AdPieSDK",
        "printedName": "AdPieSDK",
        "declKind": "Import",
        "moduleName": "BidmadAdpieAdapter"
      },
      {
        "kind": "Import",
        "name": "Combine",
        "printedName": "Combine",
        "declKind": "Import",
        "moduleName": "BidmadAdpieAdapter"
      },
      {
        "kind": "Import",
        "name": "WebKit",
        "printedName": "WebKit",
        "declKind": "Import",
        "moduleName": "BidmadAdpieAdapter"
      },
      {
        "kind": "TypeDecl",
        "name": "BidmadBannerAdpieAdapter",
        "printedName": "BidmadBannerAdpieAdapter",
        "children": [
          {
            "kind": "Function",
            "name": "loadAd",
            "printedName": "loadAd(from:with:)",
            "children": [
              {
                "kind": "TypeNominal",
                "name": "Void",
                "printedName": "()"
              },
              {
                "kind": "TypeNominal",
                "name": "UIViewController",
                "printedName": "UIKit.UIViewController",
                "usr": "c:objc(cs)UIViewController"
              },
              {
                "kind": "TypeFunc",
                "name": "Function",
                "printedName": "(BidmadSDK.BidmadBannerAdapter?, UIKit.UIView?, CoreFoundation.CGSize, (any Swift.Error)?) -> ()",
                "children": [
                  {
                    "kind": "TypeNominal",
                    "name": "Void",
                    "printedName": "()"
                  },
                  {
                    "kind": "TypeNominal",
                    "name": "Tuple",
                    "printedName": "(BidmadSDK.BidmadBannerAdapter?, UIKit.UIView?, CoreFoundation.CGSize, (any Swift.Error)?)",
                    "children": [
                      {
                        "kind": "TypeNominal",
                        "name": "Optional",
                        "printedName": "BidmadSDK.BidmadBannerAdapter?",
                        "children": [
                          {
                            "kind": "TypeNominal",
                            "name": "BidmadBannerAdapter",
                            "printedName": "BidmadSDK.BidmadBannerAdapter",
                            "usr": "c:objc(cs)BidmadBannerAdapter"
                          }
                        ],
                        "usr": "s:Sq"
                      },
                      {
                        "kind": "TypeNominal",
                        "name": "Optional",
                        "printedName": "UIKit.UIView?",
                        "children": [
                          {
                            "kind": "TypeNominal",
                            "name": "UIView",
                            "printedName": "UIKit.UIView",
                            "usr": "c:objc(cs)UIView"
                          }
                        ],
                        "usr": "s:Sq"
                      },
                      {
                        "kind": "TypeNominal",
                        "name": "CGSize",
                        "printedName": "CoreFoundation.CGSize",
                        "usr": "c:@S@CGSize"
                      },
                      {
                        "kind": "TypeNominal",
                        "name": "Optional",
                        "printedName": "(any Swift.Error)?",
                        "children": [
                          {
                            "kind": "TypeNominal",
                            "name": "Error",
                            "printedName": "any Swift.Error",
                            "usr": "s:s5ErrorP"
                          }
                        ],
                        "usr": "s:Sq"
                      }
                    ]
                  }
                ]
              }
            ],
            "declKind": "Func",
            "usr": "c:@M@BidmadAdpieAdapter@objc(cs)BidmadBannerAdpieAdapter(im)loadAdFrom:with:",
            "mangledName": "$s18BidmadAdpieAdapter0a6BannerbC0C6loadAd4from4withySo16UIViewControllerC_ySo0adC0CSg_So0I0CSgSo6CGSizeVs5Error_pSgtctF",
            "moduleName": "BidmadAdpieAdapter",
            "overriding": true,
            "objc_name": "loadAdFrom:with:",
            "declAttributes": [
              "Dynamic",
              "ObjC",
              "Override",
              "AccessControl"
            ],
            "funcSelfKind": "NonMutating"
          },
          {
            "kind": "Function",
            "name": "adViewDidLoadAd",
            "printedName": "adViewDidLoadAd(_:)",
            "children": [
              {
                "kind": "TypeNominal",
                "name": "Void",
                "printedName": "()"
              },
              {
                "kind": "TypeNominal",
                "name": "ImplicitlyUnwrappedOptional",
                "printedName": "AdPieSDK.APAdView?",
                "children": [
                  {
                    "kind": "TypeNominal",
                    "name": "APAdView",
                    "printedName": "AdPieSDK.APAdView",
                    "usr": "c:objc(cs)APAdView"
                  }
                ],
                "usr": "s:Sq"
              }
            ],
            "declKind": "Func",
            "usr": "c:@M@BidmadAdpieAdapter@objc(cs)BidmadBannerAdpieAdapter(im)adViewDidLoadAd:",
            "mangledName": "$s18BidmadAdpieAdapter0a6BannerbC0C15adViewDidLoadAdyySo04APAdF0CSgF",
            "moduleName": "BidmadAdpieAdapter",
            "objc_name": "adViewDidLoadAd:",
            "declAttributes": [
              "ObjC",
              "AccessControl"
            ],
            "funcSelfKind": "NonMutating"
          },
          {
            "kind": "Function",
            "name": "adViewDidFail",
            "printedName": "adViewDidFail(toLoadAd:withError:)",
            "children": [
              {
                "kind": "TypeNominal",
                "name": "Void",
                "printedName": "()"
              },
              {
                "kind": "TypeNominal",
                "name": "ImplicitlyUnwrappedOptional",
                "printedName": "AdPieSDK.APAdView?",
                "children": [
                  {
                    "kind": "TypeNominal",
                    "name": "APAdView",
                    "printedName": "AdPieSDK.APAdView",
                    "usr": "c:objc(cs)APAdView"
                  }
                ],
                "usr": "s:Sq"
              },
              {
                "kind": "TypeNominal",
                "name": "ImplicitlyUnwrappedOptional",
                "printedName": "(any Swift.Error)?",
                "children": [
                  {
                    "kind": "TypeNominal",
                    "name": "Error",
                    "printedName": "any Swift.Error",
                    "usr": "s:s5ErrorP"
                  }
                ],
                "usr": "s:Sq"
              }
            ],
            "declKind": "Func",
            "usr": "c:@M@BidmadAdpieAdapter@objc(cs)BidmadBannerAdpieAdapter(im)adViewDidFailToLoadAd:withError:",
            "mangledName": "$s18BidmadAdpieAdapter0a6BannerbC0C13adViewDidFail8toLoadAd9withErrorySo04APAdF0CSg_s0M0_pSgtF",
            "moduleName": "BidmadAdpieAdapter",
            "objc_name": "adViewDidFailToLoadAd:withError:",
            "declAttributes": [
              "ObjC",
              "AccessControl"
            ],
            "funcSelfKind": "NonMutating"
          },
          {
            "kind": "Function",
            "name": "destroyed",
            "printedName": "destroyed()",
            "children": [
              {
                "kind": "TypeNominal",
                "name": "Void",
                "printedName": "()"
              }
            ],
            "declKind": "Func",
            "usr": "c:@M@BidmadAdpieAdapter@objc(cs)BidmadBannerAdpieAdapter(im)destroyed",
            "mangledName": "$s18BidmadAdpieAdapter0a6BannerbC0C9destroyedyyF",
            "moduleName": "BidmadAdpieAdapter",
            "overriding": true,
            "objc_name": "destroyed",
            "declAttributes": [
              "Dynamic",
              "ObjC",
              "Override",
              "AccessControl"
            ],
            "funcSelfKind": "NonMutating"
          },
          {
            "kind": "Constructor",
            "name": "init",
            "printedName": "init(adUnit:)",
            "children": [
              {
                "kind": "TypeNominal",
                "name": "BidmadBannerAdpieAdapter",
                "printedName": "BidmadAdpieAdapter.BidmadBannerAdpieAdapter",
                "usr": "c:@M@BidmadAdpieAdapter@objc(cs)BidmadBannerAdpieAdapter"
              },
              {
                "kind": "TypeNominal",
                "name": "BidmadAdUnit",
                "printedName": "BidmadSDK.BidmadAdUnit",
                "usr": "c:@M@BidmadSDK@objc(cs)BidmadAdUnit"
              }
            ],
            "declKind": "Constructor",
            "usr": "c:@M@BidmadAdpieAdapter@objc(cs)BidmadBannerAdpieAdapter(im)initWithAdUnit:",
            "mangledName": "$s18BidmadAdpieAdapter0a6BannerbC0C6adUnitAC0A3SDK0a2AdF0C_tcfc",
            "moduleName": "BidmadAdpieAdapter",
            "overriding": true,
            "implicit": true,
            "objc_name": "initWithAdUnit:",
            "declAttributes": [
              "Dynamic",
              "ObjC",
              "Required"
            ],
            "init_kind": "Designated"
          },
          {
            "kind": "Constructor",
            "name": "init",
            "printedName": "init()",
            "children": [
              {
                "kind": "TypeNominal",
                "name": "BidmadBannerAdpieAdapter",
                "printedName": "BidmadAdpieAdapter.BidmadBannerAdpieAdapter",
                "usr": "c:@M@BidmadAdpieAdapter@objc(cs)BidmadBannerAdpieAdapter"
              }
            ],
            "declKind": "Constructor",
            "usr": "c:@M@BidmadAdpieAdapter@objc(cs)BidmadBannerAdpieAdapter(im)init",
            "mangledName": "$s18BidmadAdpieAdapter0a6BannerbC0CACycfc",
            "moduleName": "BidmadAdpieAdapter",
            "overriding": true,
            "implicit": true,
            "objc_name": "init",
            "declAttributes": [
              "Dynamic",
              "ObjC",
              "Override"
            ],
            "init_kind": "Designated"
          }
        ],
        "declKind": "Class",
        "usr": "c:@M@BidmadAdpieAdapter@objc(cs)BidmadBannerAdpieAdapter",
        "mangledName": "$s18BidmadAdpieAdapter0a6BannerbC0C",
        "moduleName": "BidmadAdpieAdapter",
        "declAttributes": [
          "AccessControl",
          "ObjC"
        ],
        "superclassUsr": "c:objc(cs)BidmadBannerAdapter",
        "inheritsConvenienceInitializers": true,
        "superclassNames": [
          "BidmadSDK.BidmadBannerAdapter",
          "ObjectiveC.NSObject"
        ],
        "conformances": [
          {
            "kind": "Conformance",
            "name": "Sendable",
            "printedName": "Sendable",
            "usr": "s:s8SendableP",
            "mangledName": "$ss8SendableP"
          },
          {
            "kind": "Conformance",
            "name": "Copyable",
            "printedName": "Copyable",
            "usr": "s:s8CopyableP",
            "mangledName": "$ss8CopyableP"
          },
          {
            "kind": "Conformance",
            "name": "Escapable",
            "printedName": "Escapable",
            "usr": "s:s9EscapableP",
            "mangledName": "$ss9EscapableP"
          },
          {
            "kind": "Conformance",
            "name": "Equatable",
            "printedName": "Equatable",
            "usr": "s:SQ",
            "mangledName": "$sSQ"
          },
          {
            "kind": "Conformance",
            "name": "Hashable",
            "printedName": "Hashable",
            "usr": "s:SH",
            "mangledName": "$sSH"
          },
          {
            "kind": "Conformance",
            "name": "CVarArg",
            "printedName": "CVarArg",
            "usr": "s:s7CVarArgP",
            "mangledName": "$ss7CVarArgP"
          },
          {
            "kind": "Conformance",
            "name": "_KeyValueCodingAndObservingPublishing",
            "printedName": "_KeyValueCodingAndObservingPublishing",
            "usr": "s:10Foundation37_KeyValueCodingAndObservingPublishingP",
            "mangledName": "$s10Foundation37_KeyValueCodingAndObservingPublishingP"
          },
          {
            "kind": "Conformance",
            "name": "_KeyValueCodingAndObserving",
            "printedName": "_KeyValueCodingAndObserving",
            "usr": "s:10Foundation27_KeyValueCodingAndObservingP",
            "mangledName": "$s10Foundation27_KeyValueCodingAndObservingP"
          },
          {
            "kind": "Conformance",
            "name": "CustomStringConvertible",
            "printedName": "CustomStringConvertible",
            "usr": "s:s23CustomStringConvertibleP",
            "mangledName": "$ss23CustomStringConvertibleP"
          },
          {
            "kind": "Conformance",
            "name": "CustomDebugStringConvertible",
            "printedName": "CustomDebugStringConvertible",
            "usr": "s:s28CustomDebugStringConvertibleP",
            "mangledName": "$ss28CustomDebugStringConvertibleP"
          },
          {
            "kind": "Conformance",
            "name": "SendableMetatype",
            "printedName": "SendableMetatype",
            "usr": "s:s16SendableMetatypeP",
            "mangledName": "$ss16SendableMetatypeP"
          }
        ]
      },
      {
        "kind": "Import",
        "name": "UIKit",
        "printedName": "UIKit",
        "declKind": "Import",
        "moduleName": "BidmadAdpieAdapter",
        "declAttributes": [
          "RawDocComment"
        ]
      },
      {
        "kind": "Import",
        "name": "BidmadSDK",
        "printedName": "BidmadSDK",
        "declKind": "Import",
        "moduleName": "BidmadAdpieAdapter"
      },
      {
        "kind": "Import",
        "name": "AdPieSDK",
        "printedName": "AdPieSDK",
        "declKind": "Import",
        "moduleName": "BidmadAdpieAdapter"
      },
      {
        "kind": "TypeDecl",
        "name": "BidmadInterstitialAdpieAdapter",
        "printedName": "BidmadInterstitialAdpieAdapter",
        "children": [
          {
            "kind": "Constructor",
            "name": "init",
            "printedName": "init(adUnit:)",
            "children": [
              {
                "kind": "TypeNominal",
                "name": "BidmadInterstitialAdpieAdapter",
                "printedName": "BidmadAdpieAdapter.BidmadInterstitialAdpieAdapter",
                "usr": "c:@M@BidmadAdpieAdapter@objc(cs)BidmadInterstitialAdpieAdapter"
              },
              {
                "kind": "TypeNominal",
                "name": "BidmadAdUnit",
                "printedName": "BidmadSDK.BidmadAdUnit",
                "usr": "c:@M@BidmadSDK@objc(cs)BidmadAdUnit"
              }
            ],
            "declKind": "Constructor",
            "usr": "c:@M@BidmadAdpieAdapter@objc(cs)BidmadInterstitialAdpieAdapter(im)initWithAdUnit:",
            "mangledName": "$s18BidmadAdpieAdapter0a12InterstitialbC0C6adUnitAC0A3SDK0a2AdF0C_tcfc",
            "moduleName": "BidmadAdpieAdapter",
            "overriding": true,
            "objc_name": "initWithAdUnit:",
            "declAttributes": [
              "Dynamic",
              "ObjC",
              "Override",
              "AccessControl"
            ],
            "init_kind": "Designated"
          },
          {
            "kind": "Function",
            "name": "loadAd",
            "printedName": "loadAd(_:)",
            "children": [
              {
                "kind": "TypeNominal",
                "name": "Void",
                "printedName": "()"
              },
              {
                "kind": "TypeFunc",
                "name": "Function",
                "printedName": "(BidmadSDK.BidmadFullscreenAdapter?, (any Swift.Error)?) -> ()",
                "children": [
                  {
                    "kind": "TypeNominal",
                    "name": "Void",
                    "printedName": "()"
                  },
                  {
                    "kind": "TypeNominal",
                    "name": "Tuple",
                    "printedName": "(BidmadSDK.BidmadFullscreenAdapter?, (any Swift.Error)?)",
                    "children": [
                      {
                        "kind": "TypeNominal",
                        "name": "Optional",
                        "printedName": "BidmadSDK.BidmadFullscreenAdapter?",
                        "children": [
                          {
                            "kind": "TypeNominal",
                            "name": "BidmadFullscreenAdapter",
                            "printedName": "BidmadSDK.BidmadFullscreenAdapter",
                            "usr": "c:objc(cs)BidmadFullscreenAdapter"
                          }
                        ],
                        "usr": "s:Sq"
                      },
                      {
                        "kind": "TypeNominal",
                        "name": "Optional",
                        "printedName": "(any Swift.Error)?",
                        "children": [
                          {
                            "kind": "TypeNominal",
                            "name": "Error",
                            "printedName": "any Swift.Error",
                            "usr": "s:s5ErrorP"
                          }
                        ],
                        "usr": "s:Sq"
                      }
                    ]
                  }
                ]
              }
            ],
            "declKind": "Func",
            "usr": "c:@M@BidmadAdpieAdapter@objc(cs)BidmadInterstitialAdpieAdapter(im)loadAdWith:",
            "mangledName": "$s18BidmadAdpieAdapter0a12InterstitialbC0C6loadAdyyySo0a10FullscreenC0CSg_s5Error_pSgtcF",
            "moduleName": "BidmadAdpieAdapter",
            "overriding": true,
            "objc_name": "loadAdWith:",
            "declAttributes": [
              "Dynamic",
              "ObjC",
              "Override",
              "AccessControl"
            ],
            "funcSelfKind": "NonMutating"
          },
          {
            "kind": "Function",
            "name": "showAd",
            "printedName": "showAd(from:)",
            "children": [
              {
                "kind": "TypeNominal",
                "name": "Void",
                "printedName": "()"
              },
              {
                "kind": "TypeNominal",
                "name": "UIViewController",
                "printedName": "UIKit.UIViewController",
                "usr": "c:objc(cs)UIViewController"
              }
            ],
            "declKind": "Func",
            "usr": "c:@M@BidmadAdpieAdapter@objc(cs)BidmadInterstitialAdpieAdapter(im)showAdFrom:",
            "mangledName": "$s18BidmadAdpieAdapter0a12InterstitialbC0C6showAd4fromySo16UIViewControllerC_tF",
            "moduleName": "BidmadAdpieAdapter",
            "overriding": true,
            "objc_name": "showAdFrom:",
            "declAttributes": [
              "Dynamic",
              "ObjC",
              "Override",
              "AccessControl"
            ],
            "funcSelfKind": "NonMutating"
          },
          {
            "kind": "Function",
            "name": "interstitialDidLoadAd",
            "printedName": "interstitialDidLoadAd(_:)",
            "children": [
              {
                "kind": "TypeNominal",
                "name": "Void",
                "printedName": "()"
              },
              {
                "kind": "TypeNominal",
                "name": "ImplicitlyUnwrappedOptional",
                "printedName": "AdPieSDK.APInterstitial?",
                "children": [
                  {
                    "kind": "TypeNominal",
                    "name": "APInterstitial",
                    "printedName": "AdPieSDK.APInterstitial",
                    "usr": "c:objc(cs)APInterstitial"
                  }
                ],
                "usr": "s:Sq"
              }
            ],
            "declKind": "Func",
            "usr": "c:@M@BidmadAdpieAdapter@objc(cs)BidmadInterstitialAdpieAdapter(im)interstitialDidLoadAd:",
            "mangledName": "$s18BidmadAdpieAdapter0a12InterstitialbC0C21interstitialDidLoadAdyySo14APInterstitialCSgF",
            "moduleName": "BidmadAdpieAdapter",
            "objc_name": "interstitialDidLoadAd:",
            "declAttributes": [
              "ObjC",
              "AccessControl"
            ],
            "funcSelfKind": "NonMutating"
          },
          {
            "kind": "Function",
            "name": "interstitialDidFail",
            "printedName": "interstitialDidFail(toLoadAd:withError:)",
            "children": [
              {
                "kind": "TypeNominal",
                "name": "Void",
                "printedName": "()"
              },
              {
                "kind": "TypeNominal",
                "name": "ImplicitlyUnwrappedOptional",
                "printedName": "AdPieSDK.APInterstitial?",
                "children": [
                  {
                    "kind": "TypeNominal",
                    "name": "APInterstitial",
                    "printedName": "AdPieSDK.APInterstitial",
                    "usr": "c:objc(cs)APInterstitial"
                  }
                ],
                "usr": "s:Sq"
              },
              {
                "kind": "TypeNominal",
                "name": "ImplicitlyUnwrappedOptional",
                "printedName": "(any Swift.Error)?",
                "children": [
                  {
                    "kind": "TypeNominal",
                    "name": "Error",
                    "printedName": "any Swift.Error",
                    "usr": "s:s5ErrorP"
                  }
                ],
                "usr": "s:Sq"
              }
            ],
            "declKind": "Func",
            "usr": "c:@M@BidmadAdpieAdapter@objc(cs)BidmadInterstitialAdpieAdapter(im)interstitialDidFailToLoadAd:withError:",
            "mangledName": "$s18BidmadAdpieAdapter0a12InterstitialbC0C19interstitialDidFail8toLoadAd9withErrorySo14APInterstitialCSg_s0L0_pSgtF",
            "moduleName": "BidmadAdpieAdapter",
            "objc_name": "interstitialDidFailToLoadAd:withError:",
            "declAttributes": [
              "ObjC",
              "AccessControl"
            ],
            "funcSelfKind": "NonMutating"
          },
          {
            "kind": "Function",
            "name": "interstitialWillPresentScreen",
            "printedName": "interstitialWillPresentScreen(_:)",
            "children": [
              {
                "kind": "TypeNominal",
                "name": "Void",
                "printedName": "()"
              },
              {
                "kind": "TypeNominal",
                "name": "ImplicitlyUnwrappedOptional",
                "printedName": "AdPieSDK.APInterstitial?",
                "children": [
                  {
                    "kind": "TypeNominal",
                    "name": "APInterstitial",
                    "printedName": "AdPieSDK.APInterstitial",
                    "usr": "c:objc(cs)APInterstitial"
                  }
                ],
                "usr": "s:Sq"
              }
            ],
            "declKind": "Func",
            "usr": "c:@M@BidmadAdpieAdapter@objc(cs)BidmadInterstitialAdpieAdapter(im)interstitialWillPresentScreen:",
            "mangledName": "$s18BidmadAdpieAdapter0a12InterstitialbC0C29interstitialWillPresentScreenyySo14APInterstitialCSgF",
            "moduleName": "BidmadAdpieAdapter",
            "objc_name": "interstitialWillPresentScreen:",
            "declAttributes": [
              "ObjC",
              "AccessControl"
            ],
            "funcSelfKind": "NonMutating"
          },
          {
            "kind": "Function",
            "name": "interstitialDidDismissScreen",
            "printedName": "interstitialDidDismissScreen(_:)",
            "children": [
              {
                "kind": "TypeNominal",
                "name": "Void",
                "printedName": "()"
              },
              {
                "kind": "TypeNominal",
                "name": "ImplicitlyUnwrappedOptional",
                "printedName": "AdPieSDK.APInterstitial?",
                "children": [
                  {
                    "kind": "TypeNominal",
                    "name": "APInterstitial",
                    "printedName": "AdPieSDK.APInterstitial",
                    "usr": "c:objc(cs)APInterstitial"
                  }
                ],
                "usr": "s:Sq"
              }
            ],
            "declKind": "Func",
            "usr": "c:@M@BidmadAdpieAdapter@objc(cs)BidmadInterstitialAdpieAdapter(im)interstitialDidDismissScreen:",
            "mangledName": "$s18BidmadAdpieAdapter0a12InterstitialbC0C28interstitialDidDismissScreenyySo14APInterstitialCSgF",
            "moduleName": "BidmadAdpieAdapter",
            "objc_name": "interstitialDidDismissScreen:",
            "declAttributes": [
              "ObjC",
              "AccessControl"
            ],
            "funcSelfKind": "NonMutating"
          },
          {
            "kind": "Function",
            "name": "interstitialWillLeaveApplication",
            "printedName": "interstitialWillLeaveApplication(_:)",
            "children": [
              {
                "kind": "TypeNominal",
                "name": "Void",
                "printedName": "()"
              },
              {
                "kind": "TypeNominal",
                "name": "ImplicitlyUnwrappedOptional",
                "printedName": "AdPieSDK.APInterstitial?",
                "children": [
                  {
                    "kind": "TypeNominal",
                    "name": "APInterstitial",
                    "printedName": "AdPieSDK.APInterstitial",
                    "usr": "c:objc(cs)APInterstitial"
                  }
                ],
                "usr": "s:Sq"
              }
            ],
            "declKind": "Func",
            "usr": "c:@M@BidmadAdpieAdapter@objc(cs)BidmadInterstitialAdpieAdapter(im)interstitialWillLeaveApplication:",
            "mangledName": "$s18BidmadAdpieAdapter0a12InterstitialbC0C32interstitialWillLeaveApplicationyySo14APInterstitialCSgF",
            "moduleName": "BidmadAdpieAdapter",
            "objc_name": "interstitialWillLeaveApplication:",
            "declAttributes": [
              "ObjC",
              "AccessControl"
            ],
            "funcSelfKind": "NonMutating"
          },
          {
            "kind": "Constructor",
            "name": "init",
            "printedName": "init()",
            "children": [
              {
                "kind": "TypeNominal",
                "name": "BidmadInterstitialAdpieAdapter",
                "printedName": "BidmadAdpieAdapter.BidmadInterstitialAdpieAdapter",
                "usr": "c:@M@BidmadAdpieAdapter@objc(cs)BidmadInterstitialAdpieAdapter"
              }
            ],
            "declKind": "Constructor",
            "usr": "c:@M@BidmadAdpieAdapter@objc(cs)BidmadInterstitialAdpieAdapter(im)init",
            "mangledName": "$s18BidmadAdpieAdapter0a12InterstitialbC0CACycfc",
            "moduleName": "BidmadAdpieAdapter",
            "overriding": true,
            "implicit": true,
            "objc_name": "init",
            "declAttributes": [
              "Dynamic",
              "ObjC",
              "Override"
            ],
            "init_kind": "Designated"
          }
        ],
        "declKind": "Class",
        "usr": "c:@M@BidmadAdpieAdapter@objc(cs)BidmadInterstitialAdpieAdapter",
        "mangledName": "$s18BidmadAdpieAdapter0a12InterstitialbC0C",
        "moduleName": "BidmadAdpieAdapter",
        "declAttributes": [
          "AccessControl",
          "ObjC"
        ],
        "superclassUsr": "c:objc(cs)BidmadFullscreenAdapter",
        "superclassNames": [
          "BidmadSDK.BidmadFullscreenAdapter",
          "ObjectiveC.NSObject"
        ],
        "conformances": [
          {
            "kind": "Conformance",
            "name": "Sendable",
            "printedName": "Sendable",
            "usr": "s:s8SendableP",
            "mangledName": "$ss8SendableP"
          },
          {
            "kind": "Conformance",
            "name": "Copyable",
            "printedName": "Copyable",
            "usr": "s:s8CopyableP",
            "mangledName": "$ss8CopyableP"
          },
          {
            "kind": "Conformance",
            "name": "Escapable",
            "printedName": "Escapable",
            "usr": "s:s9EscapableP",
            "mangledName": "$ss9EscapableP"
          },
          {
            "kind": "Conformance",
            "name": "Equatable",
            "printedName": "Equatable",
            "usr": "s:SQ",
            "mangledName": "$sSQ"
          },
          {
            "kind": "Conformance",
            "name": "Hashable",
            "printedName": "Hashable",
            "usr": "s:SH",
            "mangledName": "$sSH"
          },
          {
            "kind": "Conformance",
            "name": "CVarArg",
            "printedName": "CVarArg",
            "usr": "s:s7CVarArgP",
            "mangledName": "$ss7CVarArgP"
          },
          {
            "kind": "Conformance",
            "name": "_KeyValueCodingAndObservingPublishing",
            "printedName": "_KeyValueCodingAndObservingPublishing",
            "usr": "s:10Foundation37_KeyValueCodingAndObservingPublishingP",
            "mangledName": "$s10Foundation37_KeyValueCodingAndObservingPublishingP"
          },
          {
            "kind": "Conformance",
            "name": "_KeyValueCodingAndObserving",
            "printedName": "_KeyValueCodingAndObserving",
            "usr": "s:10Foundation27_KeyValueCodingAndObservingP",
            "mangledName": "$s10Foundation27_KeyValueCodingAndObservingP"
          },
          {
            "kind": "Conformance",
            "name": "CustomStringConvertible",
            "printedName": "CustomStringConvertible",
            "usr": "s:s23CustomStringConvertibleP",
            "mangledName": "$ss23CustomStringConvertibleP"
          },
          {
            "kind": "Conformance",
            "name": "CustomDebugStringConvertible",
            "printedName": "CustomDebugStringConvertible",
            "usr": "s:s28CustomDebugStringConvertibleP",
            "mangledName": "$ss28CustomDebugStringConvertibleP"
          },
          {
            "kind": "Conformance",
            "name": "SendableMetatype",
            "printedName": "SendableMetatype",
            "usr": "s:s16SendableMetatypeP",
            "mangledName": "$ss16SendableMetatypeP"
          }
        ]
      }
    ],
    "json_format_version": 8
  },
  "ConstValues": [
    {
      "filePath": "\/Users\/markus\/Documents\/GitHub\/BidmadSDK-DevSuite-NextGen\/BidmadAdpieAdapter\/Sources\/BMAdPieManagerLegacySupport.swift",
      "kind": "StringLiteral",
      "offset": 333,
      "length": 32,
      "value": "\"com.bidmad.adpie.manager.state\""
    }
  ]
}